{
  "db_name": "PostgreSQL",
  "query": "INSERT INTO player\n        (number, name, username, email)\n        VALUES ($1, $2, $3, $4)\n        RETURNING number, name, username, email",
  "describe": {
    "columns": [
      {
        "ordinal": 0,
        "name": "number",
        "type_info": "Int4"
      },
      {
        "ordinal": 1,
        "name": "name",
        "type_info": "Text"
      },
      {
        "ordinal": 2,
        "name": "username",
        "type_info": "Text"
      },
      {
        "ordinal": 3,
        "name": "email",
        "type_info": "Text"
      }
    ],
    "parameters": {
      "Left": [
        "Int4",
        "Text",
        "Text",
        "Text"
      ]
    },
    "nullable": [
      false,
      false,
      false,
      true
    ]
  },
  "hash": "011b7bfd8d8db7e3d13179d4c93dbb0b37af95a60f9ad56e739d8e66400477f1"
}
